cado/__init__.py
cado/app/__init__.py
cado/app/app.py
cado/app/disk.py
cado/app/example.py
cado/app/message.py
cado/app/response.py
cado/app/routes.py
cado/app/session_state.py
cado/cli/__init__.py
cado/cli/cli.py
cado/core/__init__.py
cado/core/cell.py
cado/core/cell_status.py
cado/core/language.py
cado/core/notebook.py
cado/core/notebook_details.py
cado/examples/.gitignore
cado/examples/__init__.py
cado/examples/example.cado
cado/examples/is-even.cado
cado/ui/.gitignore
cado/ui/dist/assets/cado-4c2ab5b5.png
cado/ui/dist/assets/index-8b1fee66.css
cado/ui/dist/assets/index-de48be89.js
cado/ui/dist/assets/poppins-all-400-normal-c68e1edb.woff
cado/ui/dist/assets/poppins-all-700-normal-282b1ac4.woff
cado/ui/dist/assets/poppins-devanagari-400-normal-478b3ab7.woff2
cado/ui/dist/assets/poppins-devanagari-700-normal-6197a412.woff2
cado/ui/dist/assets/poppins-latin-400-normal-7d93459d.woff2
cado/ui/dist/assets/poppins-latin-700-normal-9338e65f.woff2
cado/ui/dist/assets/poppins-latin-ext-400-normal-cb8bdeab.woff2
cado/ui/dist/assets/poppins-latin-ext-700-normal-4ce2c84c.woff2
cado/ui/dist/assets/sen-all-400-normal-f948c17e.woff
cado/ui/dist/assets/sen-all-700-normal-c125c762.woff
cado/ui/dist/assets/sen-latin-400-normal-952d0124.woff2
cado/ui/dist/assets/sen-latin-700-normal-0d815a4a.woff2
cado/ui/dist/assets/sen-latin-ext-400-normal-9e66b194.woff2
cado/ui/dist/assets/sen-latin-ext-700-normal-3dd7ec03.woff2
cado/ui/dist/cado.png
cado/ui/dist/index.html
cado/ui/index.html
cado/ui/package-lock.json
cado/ui/package.json
cado/ui/postcss.config.cjs
cado/ui/public/cado.png
cado/ui/src/components/App.tsx
cado/ui/src/components/Cell.tsx
cado/ui/src/components/Connection.tsx
cado/ui/src/components/Disconnect.tsx
cado/ui/src/components/Notebook.tsx
cado/ui/src/components/Notebooks.tsx
cado/ui/src/components/Toolbar.tsx
cado/ui/src/hooks/image.ts
cado/ui/src/hooks/keys.ts
cado/ui/src/images/cado.png
cado/ui/src/index.css
cado/ui/src/index.tsx
cado/ui/src/lib/appConfig.ts
cado-0.1.8.dist-info/WHEEL
cado-0.1.8.dist-info/entry_points.txt
cado-0.1.8.dist-info/LICENSE.txt
cado-0.1.8.dist-info/METADATA
cado-0.1.8.dist-info/RECORD
