Metadata-Version: 2.1
Name: cado
Version: 0.1.8
Summary: Python notebook development environment.
Home-page: https://github.com/gregorybchris/cado
License: Apache Software License
Keywords: python,notebook,development,environment
Author: Chris Gregory
Author-email: christopher.b.gregory@gmail.com
Requires-Python: >=3.8.1,<4
Classifier: Development Status :: 5 - Production/Stable
Classifier: Intended Audience :: Developers
Classifier: License :: OSI Approved :: Apache Software License
Classifier: License :: Other/Proprietary License
Classifier: Programming Language :: Python
Classifier: Programming Language :: Python :: 3
Classifier: Programming Language :: Python :: 3.9
Classifier: Programming Language :: Python :: 3.10
Classifier: Programming Language :: Python :: 3.11
Classifier: Programming Language :: Python :: 3.10
Classifier: Programming Language :: Python :: 3.8
Classifier: Programming Language :: Python :: 3.9
Classifier: Topic :: Software Development
Requires-Dist: click (>=8.1.3,<9.0.0)
Requires-Dist: fastapi (>=0.70.0,<0.71.0)
Requires-Dist: pydantic (>=1.9.0,<2.0.0)
Requires-Dist: uvicorn[standard] (>=0.15.0,<0.16.0)
Project-URL: Repository, https://github.com/gregorybchris/cado
